{
  "name": "Monokai Islands Light",
  "dark": false,
  "author": "Bart Smykla",
  "editorScheme": "/editor-schemes/monokai-islands-light.xml",
  "parent": "Islands Light",
  "islands": 1,
  "ui": {
    "MainWindow.background": "#f5f4f5",
    "ToolWindow.background": "#f9f9fa",
    "ToolWindow.Header.background": "#f9f9fa",
    "EditorTabs.background": "#f9f9fa",
    "EditorTabs.underlineColor": "#f0144a",
    "EditorTabs.underlinedBorderColor": "#f0144a",
    "Island.borderColor": "#f9f9fa",
    "Island.arc": 20,
    "Island.borderWidth": 5,
    "StatusBar.borderColor": "#00000000",
    "ToolWindow.Stripe.borderColor": "#00000000",
    "MainToolbar.borderColor": "#00000000",
    "Tree.selectionBackground": "#33313480",
    "Tree.selectionForeground": "#2d2a2e",
    "List.selectionBackground": "#33313480",
    "List.selectionForeground": "#2d2a2e",
    "Button.default.startBackground": "#38bbcb",
    "Button.default.endBackground": "#38bbcb",
    "Button.default.foreground": "#f5f4f5",
    "Button.default.focusedBorderColor": "#38bbcb",
    "Component.focusedBorderColor": "#38bbcb",
    "CompletionPopup.selectionBackground": "#333134",
    "CompletionPopup.selectionInactiveBackground": "#33313460",
    "SearchEverywhere.Tab.selectedBackground": "#333134",
    "SearchMatch.startBackground": "#f0b91840",
    "SearchMatch.endBackground": "#f0b91840",
    "VersionControl.GitLog.localBranchIconColor": "#7bb540",
    "VersionControl.GitLog.remoteBranchIconColor": "#38bbcb",
    "VersionControl.GitLog.tagIconColor": "#eb601b",
    "Notification.errorBackground": "#f0144a20",
    "Notification.errorBorderColor": "#f0144a",
    "Notification.warningBackground": "#f0b91820",
    "Notification.warningBorderColor": "#f0b918",
    "Popup.borderColor": "#333134",
    "Popup.Header.activeBackground": "#333134",
    "Popup.Header.inactiveBackground": "#f9f9fa",
    "ProgressBar.progressColor": "#38bbcb",
    "ProgressBar.indeterminateStartColor": "#38bbcb",
    "ProgressBar.indeterminateEndColor": "#6d58db",
    "Link.activeForeground": "#38bbcb",
    "Link.hoverForeground": "#38bbcb",
    "Link.visitedForeground": "#6d58db"
  }
}
